{
    "Meta Data": {
        "1. Information": "Intraday (5min) open, high, low, close prices and volume",
        "2. Symbol": "NVDA",
        "3. Last Refreshed": "2024-11-05 19:55:00",
        "4. Interval": "5min",
        "5. Output Size": "Compact",
        "6. Time Zone": "US/Eastern"
    },
    "Time Series (5min)": {
        "2024-11-05 19:55:00": {
            "1. open": "140.1500",
            "2. high": "140.2300",
            "3. low": "140.1100",
            "4. close": "140.1650",
            "5. volume": "108710"
        },
        "2024-11-05 19:50:00": {
            "1. open": "140.1700",
            "2. high": "140.1700",
            "3. low": "140.0000",
            "4. close": "140.1600",
            "5. volume": "67217"
        },
        "2024-11-05 19:45:00": {
            "1. open": "140.2500",
            "2. high": "140.3000",
            "3. low": "140.1301",
            "4. close": "140.1700",
            "5. volume": "84447"
        },
        "2024-11-05 19:40:00": {
            "1. open": "140.2000",
            "2. high": "140.2800",
            "3. low": "140.1700",
            "4. close": "140.2300",
            "5. volume": "93022"
        },
        "2024-11-05 19:35:00": {
            "1. open": "140.1200",
            "2. high": "140.2400",
            "3. low": "140.1100",
            "4. close": "140.1700",
            "5. volume": "91765"
        },
        "2024-11-05 19:30:00": {
            "1. open": "139.9200",
            "2. high": "140.1200",
            "3. low": "139.8700",
            "4. close": "140.1100",
            "5. volume": "105456"
        },
        "2024-11-05 19:25:00": {
            "1. open": "139.8700",
            "2. high": "140.0000",
            "3. low": "139.8000",
            "4. close": "139.9999",
            "5. volume": "64443"
        },
        "2024-11-05 19:20:00": {
            "1. open": "139.8800",
            "2. high": "140.0000",
            "3. low": "139.8500",
            "4. close": "139.8700",
            "5. volume": "83099"
        },
        "2024-11-05 19:15:00": {
            "1. open": "139.7900",
            "2. high": "139.8900",
            "3. low": "139.7500",
            "4. close": "139.8700",
            "5. volume": "34307"
        },
        "2024-11-05 19:10:00": {
            "1. open": "139.7800",
            "2. high": "139.8000",
            "3. low": "139.7000",
            "4. close": "139.7800",
            "5. volume": "23389"
        },
        "2024-11-05 19:05:00": {
            "1. open": "139.7600",
            "2. high": "139.8100",
            "3. low": "139.7400",
            "4. close": "139.7500",
            "5. volume": "24801"
        },
        "2024-11-05 19:00:00": {
            "1. open": "139.6900",
            "2. high": "139.7900",
            "3. low": "139.6700",
            "4. close": "139.7700",
            "5. volume": "32756"
        },
        "2024-11-05 18:55:00": {
            "1. open": "139.7650",
            "2. high": "139.7700",
            "3. low": "139.6500",
            "4. close": "139.6900",
            "5. volume": "25171"
        },
        "2024-11-05 18:50:00": {
            "1. open": "139.7100",
            "2. high": "139.7700",
            "3. low": "139.7100",
            "4. close": "139.7600",
            "5. volume": "22478"
        },
        "2024-11-05 18:45:00": {
            "1. open": "139.6800",
            "2. high": "139.7500",
            "3. low": "139.6600",
            "4. close": "139.7300",
            "5. volume": "14888"
        },
        "2024-11-05 18:40:00": {
            "1. open": "139.6800",
            "2. high": "139.7300",
            "3. low": "139.6600",
            "4. close": "139.6900",
            "5. volume": "13213"
        },
        "2024-11-05 18:35:00": {
            "1. open": "139.7500",
            "2. high": "139.7800",
            "3. low": "139.6500",
            "4. close": "139.6800",
            "5. volume": "17224"
        },
        "2024-11-05 18:30:00": {
            "1. open": "139.6500",
            "2. high": "139.7700",
            "3. low": "139.6200",
            "4. close": "139.7550",
            "5. volume": "22106"
        },
        "2024-11-05 18:25:00": {
            "1. open": "139.5800",
            "2. high": "139.6500",
            "3. low": "139.5800",
            "4. close": "139.6500",
            "5. volume": "24126"
        },
        "2024-11-05 18:20:00": {
            "1. open": "139.6000",
            "2. high": "139.6400",
            "3. low": "139.5800",
            "4. close": "139.5900",
            "5. volume": "13370"
        },
        "2024-11-05 18:15:00": {
            "1. open": "139.6100",
            "2. high": "139.6200",
            "3. low": "139.5700",
            "4. close": "139.6200",
            "5. volume": "18361"
        },
        "2024-11-05 18:10:00": {
            "1. open": "139.5600",
            "2. high": "139.6800",
            "3. low": "139.5600",
            "4. close": "139.6200",
            "5. volume": "14540"
        },
        "2024-11-05 18:05:00": {
            "1. open": "139.5500",
            "2. high": "139.6500",
            "3. low": "139.5200",
            "4. close": "139.6300",
            "5. volume": "30611"
        },
        "2024-11-05 18:00:00": {
            "1. open": "139.6500",
            "2. high": "139.6500",
            "3. low": "139.1300",
            "4. close": "139.5500",
            "5. volume": "13708"
        },
        "2024-11-05 17:55:00": {
            "1. open": "139.5300",
            "2. high": "139.6500",
            "3. low": "139.5200",
            "4. close": "139.6500",
            "5. volume": "21605"
        },
        "2024-11-05 17:50:00": {
            "1. open": "139.5377",
            "2. high": "139.6000",
            "3. low": "139.5100",
            "4. close": "139.5400",
            "5. volume": "22663"
        },
        "2024-11-05 17:45:00": {
            "1. open": "139.5000",
            "2. high": "139.6000",
            "3. low": "139.4800",
            "4. close": "139.5500",
            "5. volume": "39811"
        },
        "2024-11-05 17:40:00": {
            "1. open": "139.5200",
            "2. high": "139.5800",
            "3. low": "139.4800",
            "4. close": "139.5400",
            "5. volume": "30281"
        },
        "2024-11-05 17:35:00": {
            "1. open": "139.6700",
            "2. high": "139.6800",
            "3. low": "139.5000",
            "4. close": "139.5200",
            "5. volume": "66026"
        },
        "2024-11-05 17:30:00": {
            "1. open": "139.6000",
            "2. high": "139.6900",
            "3. low": "139.5800",
            "4. close": "139.6700",
            "5. volume": "25062"
        },
        "2024-11-05 17:25:00": {
            "1. open": "139.5700",
            "2. high": "139.6500",
            "3. low": "139.5500",
            "4. close": "139.6400",
            "5. volume": "37617"
        },
        "2024-11-05 17:20:00": {
            "1. open": "139.6900",
            "2. high": "139.7000",
            "3. low": "139.5400",
            "4. close": "139.5800",
            "5. volume": "58090"
        },
        "2024-11-05 17:15:00": {
            "1. open": "139.6700",
            "2. high": "139.6900",
            "3. low": "139.6400",
            "4. close": "139.6800",
            "5. volume": "19100"
        },
        "2024-11-05 17:10:00": {
            "1. open": "139.6706",
            "2. high": "139.7100",
            "3. low": "139.6500",
            "4. close": "139.6500",
            "5. volume": "35012"
        },
        "2024-11-05 17:05:00": {
            "1. open": "139.6900",
            "2. high": "139.7500",
            "3. low": "139.6400",
            "4. close": "139.6600",
            "5. volume": "24081"
        },
        "2024-11-05 17:00:00": {
            "1. open": "139.7300",
            "2. high": "147.8330",
            "3. low": "135.6909",
            "4. close": "139.7000",
            "5. volume": "72573"
        },
        "2024-11-05 16:55:00": {
            "1. open": "139.5000",
            "2. high": "143.2865",
            "3. low": "137.8095",
            "4. close": "139.7300",
            "5. volume": "335283"
        },
        "2024-11-05 16:50:00": {
            "1. open": "139.4900",
            "2. high": "147.8330",
            "3. low": "139.4200",
            "4. close": "139.4800",
            "5. volume": "89582"
        },
        "2024-11-05 16:45:00": {
            "1. open": "139.5800",
            "2. high": "139.7800",
            "3. low": "135.6909",
            "4. close": "139.4300",
            "5. volume": "99680"
        },
        "2024-11-05 16:40:00": {
            "1. open": "139.6000",
            "2. high": "139.9100",
            "3. low": "139.5300",
            "4. close": "139.5800",
            "5. volume": "66160"
        },
        "2024-11-05 16:35:00": {
            "1. open": "139.6900",
            "2. high": "139.7700",
            "3. low": "139.5800",
            "4. close": "139.5900",
            "5. volume": "127215"
        },
        "2024-11-05 16:30:00": {
            "1. open": "139.6600",
            "2. high": "139.8000",
            "3. low": "139.6000",
            "4. close": "139.7000",
            "5. volume": "76926"
        },
        "2024-11-05 16:25:00": {
            "1. open": "139.8000",
            "2. high": "139.8500",
            "3. low": "139.6500",
            "4. close": "139.6700",
            "5. volume": "64920"
        },
        "2024-11-05 16:20:00": {
            "1. open": "139.7400",
            "2. high": "139.9100",
            "3. low": "139.5500",
            "4. close": "139.7500",
            "5. volume": "318974"
        },
        "2024-11-05 16:15:00": {
            "1. open": "140.0000",
            "2. high": "140.0500",
            "3. low": "139.6300",
            "4. close": "139.7000",
            "5. volume": "602301"
        },
        "2024-11-05 16:10:00": {
            "1. open": "140.0300",
            "2. high": "140.0300",
            "3. low": "134.3150",
            "4. close": "140.0100",
            "5. volume": "123044"
        },
        "2024-11-05 16:05:00": {
            "1. open": "139.9200",
            "2. high": "140.0700",
            "3. low": "139.9100",
            "4. close": "140.0200",
            "5. volume": "303668"
        },
        "2024-11-05 16:00:00": {
            "1. open": "139.9100",
            "2. high": "139.9700",
            "3. low": "139.7000",
            "4. close": "139.9150",
            "5. volume": "28868047"
        },
        "2024-11-05 15:55:00": {
            "1. open": "139.6300",
            "2. high": "139.9500",
            "3. low": "139.5200",
            "4. close": "139.9100",
            "5. volume": "4517345"
        },
        "2024-11-05 15:50:00": {
            "1. open": "139.5700",
            "2. high": "139.8000",
            "3. low": "139.4450",
            "4. close": "139.6250",
            "5. volume": "2523690"
        },
        "2024-11-05 15:45:00": {
            "1. open": "139.3200",
            "2. high": "139.6000",
            "3. low": "139.1293",
            "4. close": "139.5789",
            "5. volume": "2033911"
        },
        "2024-11-05 15:40:00": {
            "1. open": "139.5300",
            "2. high": "139.5300",
            "3. low": "139.1900",
            "4. close": "139.3189",
            "5. volume": "2167998"
        },
        "2024-11-05 15:35:00": {
            "1. open": "139.8200",
            "2. high": "139.9100",
            "3. low": "139.5300",
            "4. close": "139.5399",
            "5. volume": "1444069"
        },
        "2024-11-05 15:30:00": {
            "1. open": "139.8600",
            "2. high": "139.8799",
            "3. low": "139.5500",
            "4. close": "139.8200",
            "5. volume": "1737399"
        },
        "2024-11-05 15:25:00": {
            "1. open": "139.6307",
            "2. high": "139.8800",
            "3. low": "139.5600",
            "4. close": "139.8700",
            "5. volume": "1064668"
        },
        "2024-11-05 15:20:00": {
            "1. open": "139.8150",
            "2. high": "139.8150",
            "3. low": "139.6100",
            "4. close": "139.6373",
            "5. volume": "1047682"
        },
        "2024-11-05 15:15:00": {
            "1. open": "139.6691",
            "2. high": "139.8300",
            "3. low": "139.5800",
            "4. close": "139.8150",
            "5. volume": "1006041"
        },
        "2024-11-05 15:10:00": {
            "1. open": "139.6400",
            "2. high": "139.7200",
            "3. low": "139.5700",
            "4. close": "139.6650",
            "5. volume": "1086862"
        },
        "2024-11-05 15:05:00": {
            "1. open": "139.3300",
            "2. high": "139.6600",
            "3. low": "139.3300",
            "4. close": "139.6350",
            "5. volume": "1081242"
        },
        "2024-11-05 15:00:00": {
            "1. open": "139.4299",
            "2. high": "139.4600",
            "3. low": "139.2501",
            "4. close": "139.3293",
            "5. volume": "1287182"
        },
        "2024-11-05 14:55:00": {
            "1. open": "139.4800",
            "2. high": "139.5491",
            "3. low": "139.2900",
            "4. close": "139.4250",
            "5. volume": "1526930"
        },
        "2024-11-05 14:50:00": {
            "1. open": "139.7401",
            "2. high": "139.7423",
            "3. low": "139.4000",
            "4. close": "139.4869",
            "5. volume": "1570547"
        },
        "2024-11-05 14:45:00": {
            "1. open": "139.8850",
            "2. high": "139.9200",
            "3. low": "139.7100",
            "4. close": "139.7499",
            "5. volume": "884577"
        },
        "2024-11-05 14:40:00": {
            "1. open": "139.8850",
            "2. high": "139.9500",
            "3. low": "139.8150",
            "4. close": "139.8900",
            "5. volume": "800772"
        },
        "2024-11-05 14:35:00": {
            "1. open": "139.8500",
            "2. high": "139.9500",
            "3. low": "139.8000",
            "4. close": "139.8807",
            "5. volume": "965300"
        },
        "2024-11-05 14:30:00": {
            "1. open": "139.8250",
            "2. high": "139.9000",
            "3. low": "139.7600",
            "4. close": "139.8400",
            "5. volume": "810673"
        },
        "2024-11-05 14:25:00": {
            "1. open": "139.7500",
            "2. high": "140.0000",
            "3. low": "139.7301",
            "4. close": "139.8200",
            "5. volume": "1839942"
        },
        "2024-11-05 14:20:00": {
            "1. open": "139.7501",
            "2. high": "139.7700",
            "3. low": "139.6002",
            "4. close": "139.7499",
            "5. volume": "719604"
        },
        "2024-11-05 14:15:00": {
            "1. open": "139.7500",
            "2. high": "139.7600",
            "3. low": "139.5700",
            "4. close": "139.7500",
            "5. volume": "936752"
        },
        "2024-11-05 14:10:00": {
            "1. open": "139.6987",
            "2. high": "139.8000",
            "3. low": "139.6500",
            "4. close": "139.7600",
            "5. volume": "1074800"
        },
        "2024-11-05 14:05:00": {
            "1. open": "139.5101",
            "2. high": "139.7000",
            "3. low": "139.4400",
            "4. close": "139.6902",
            "5. volume": "970077"
        },
        "2024-11-05 14:00:00": {
            "1. open": "139.2750",
            "2. high": "139.6100",
            "3. low": "139.2750",
            "4. close": "139.5199",
            "5. volume": "1298524"
        },
        "2024-11-05 13:55:00": {
            "1. open": "139.2501",
            "2. high": "139.3200",
            "3. low": "139.1900",
            "4. close": "139.2750",
            "5. volume": "791783"
        },
        "2024-11-05 13:50:00": {
            "1. open": "139.3000",
            "2. high": "139.3400",
            "3. low": "139.1601",
            "4. close": "139.2599",
            "5. volume": "908001"
        },
        "2024-11-05 13:45:00": {
            "1. open": "139.2900",
            "2. high": "139.4200",
            "3. low": "139.1800",
            "4. close": "139.2920",
            "5. volume": "894290"
        },
        "2024-11-05 13:40:00": {
            "1. open": "139.2693",
            "2. high": "139.4300",
            "3. low": "139.1300",
            "4. close": "139.2900",
            "5. volume": "1676687"
        },
        "2024-11-05 13:35:00": {
            "1. open": "139.5887",
            "2. high": "139.6399",
            "3. low": "139.0800",
            "4. close": "139.2700",
            "5. volume": "1977564"
        },
        "2024-11-05 13:30:00": {
            "1. open": "139.5700",
            "2. high": "139.7400",
            "3. low": "139.5200",
            "4. close": "139.5877",
            "5. volume": "1019446"
        },
        "2024-11-05 13:25:00": {
            "1. open": "139.7400",
            "2. high": "139.7600",
            "3. low": "139.4600",
            "4. close": "139.5601",
            "5. volume": "1277132"
        },
        "2024-11-05 13:20:00": {
            "1. open": "139.8400",
            "2. high": "139.8700",
            "3. low": "139.6550",
            "4. close": "139.7350",
            "5. volume": "875368"
        },
        "2024-11-05 13:15:00": {
            "1. open": "139.7100",
            "2. high": "139.9400",
            "3. low": "139.7000",
            "4. close": "139.8350",
            "5. volume": "898736"
        },
        "2024-11-05 13:10:00": {
            "1. open": "139.9650",
            "2. high": "139.9695",
            "3. low": "139.6600",
            "4. close": "139.7007",
            "5. volume": "1148687"
        },
        "2024-11-05 13:05:00": {
            "1. open": "139.8040",
            "2. high": "139.9700",
            "3. low": "139.7401",
            "4. close": "139.9650",
            "5. volume": "898879"
        },
        "2024-11-05 13:00:00": {
            "1. open": "139.6700",
            "2. high": "139.8600",
            "3. low": "139.5900",
            "4. close": "139.8097",
            "5. volume": "988513"
        },
        "2024-11-05 12:55:00": {
            "1. open": "139.7500",
            "2. high": "139.7853",
            "3. low": "139.4800",
            "4. close": "139.6650",
            "5. volume": "1296801"
        },
        "2024-11-05 12:50:00": {
            "1. open": "139.9299",
            "2. high": "139.9300",
            "3. low": "139.7100",
            "4. close": "139.7490",
            "5. volume": "857782"
        },
        "2024-11-05 12:45:00": {
            "1. open": "139.5500",
            "2. high": "139.9300",
            "3. low": "139.5450",
            "4. close": "139.9200",
            "5. volume": "1480634"
        },
        "2024-11-05 12:40:00": {
            "1. open": "139.4500",
            "2. high": "139.5870",
            "3. low": "139.4000",
            "4. close": "139.5499",
            "5. volume": "980388"
        },
        "2024-11-05 12:35:00": {
            "1. open": "139.5282",
            "2. high": "139.6300",
            "3. low": "139.3500",
            "4. close": "139.4400",
            "5. volume": "1802126"
        },
        "2024-11-05 12:30:00": {
            "1. open": "139.6950",
            "2. high": "139.7900",
            "3. low": "139.5200",
            "4. close": "139.5299",
            "5. volume": "1587279"
        },
        "2024-11-05 12:25:00": {
            "1. open": "139.8850",
            "2. high": "139.8889",
            "3. low": "139.6200",
            "4. close": "139.6904",
            "5. volume": "1109664"
        },
        "2024-11-05 12:20:00": {
            "1. open": "139.9750",
            "2. high": "140.0000",
            "3. low": "139.7400",
            "4. close": "139.8850",
            "5. volume": "1280796"
        },
        "2024-11-05 12:15:00": {
            "1. open": "140.0000",
            "2. high": "140.0600",
            "3. low": "139.9000",
            "4. close": "139.9787",
            "5. volume": "1294417"
        },
        "2024-11-05 12:10:00": {
            "1. open": "139.9100",
            "2. high": "140.0300",
            "3. low": "139.7300",
            "4. close": "139.9990",
            "5. volume": "2315798"
        },
        "2024-11-05 12:05:00": {
            "1. open": "139.9990",
            "2. high": "140.0400",
            "3. low": "139.8800",
            "4. close": "139.9000",
            "5. volume": "1055393"
        },
        "2024-11-05 12:00:00": {
            "1. open": "140.3700",
            "2. high": "140.3701",
            "3. low": "139.9100",
            "4. close": "139.9934",
            "5. volume": "2107292"
        },
        "2024-11-05 11:55:00": {
            "1. open": "140.1890",
            "2. high": "140.3700",
            "3. low": "140.1750",
            "4. close": "140.3650",
            "5. volume": "2218401"
        },
        "2024-11-05 11:50:00": {
            "1. open": "139.9450",
            "2. high": "140.1900",
            "3. low": "139.8300",
            "4. close": "140.1801",
            "5. volume": "3323861"
        },
        "2024-11-05 11:45:00": {
            "1. open": "139.8150",
            "2. high": "140.0000",
            "3. low": "139.7800",
            "4. close": "139.9402",
            "5. volume": "1880163"
        },
        "2024-11-05 11:40:00": {
            "1. open": "139.8600",
            "2. high": "139.8700",
            "3. low": "139.7609",
            "4. close": "139.8100",
            "5. volume": "947018"
        }
    }
}