{
    "Meta Data": {
        "1. Information": "Intraday (5min) open, high, low, close prices and volume",
        "2. Symbol": "SPY",
        "3. Last Refreshed": "2025-04-08 20:00:00",
        "4. Interval": "5min",
        "5. Output Size": "Compact",
        "6. Time Zone": "US/Eastern"
    },
    "Time Series (5min)": {
        "2025-04-08 20:00:00": {
            "1. open": "496.4800",
            "2. high": "496.4800",
            "3. low": "496.4800",
            "4. close": "496.4800",
            "5. volume": "2994872"
        },
        "2025-04-08 19:55:00": {
            "1. open": "489.5300",
            "2. high": "490.6300",
            "3. low": "489.3700",
            "4. close": "490.5550",
            "5. volume": "69977"
        },
        "2025-04-08 19:50:00": {
            "1. open": "489.7600",
            "2. high": "490.1400",
            "3. low": "488.9000",
            "4. close": "489.6100",
            "5. volume": "29523"
        },
        "2025-04-08 19:45:00": {
            "1. open": "487.8700",
            "2. high": "490.0800",
            "3. low": "487.7350",
            "4. close": "489.8200",
            "5. volume": "95865"
        },
        "2025-04-08 19:40:00": {
            "1. open": "488.9800",
            "2. high": "489.3300",
            "3. low": "487.7600",
            "4. close": "487.8150",
            "5. volume": "25429"
        },
        "2025-04-08 19:35:00": {
            "1. open": "487.9800",
            "2. high": "489.1300",
            "3. low": "487.9800",
            "4. close": "488.9850",
            "5. volume": "76615"
        },
        "2025-04-08 19:30:00": {
            "1. open": "488.2400",
            "2. high": "488.3900",
            "3. low": "487.8900",
            "4. close": "488.0000",
            "5. volume": "56900"
        },
        "2025-04-08 19:25:00": {
            "1. open": "488.6800",
            "2. high": "489.3000",
            "3. low": "487.8200",
            "4. close": "488.1000",
            "5. volume": "63507"
        },
        "2025-04-08 19:20:00": {
            "1. open": "489.7200",
            "2. high": "489.7200",
            "3. low": "488.0500",
            "4. close": "488.6800",
            "5. volume": "75448"
        },
        "2025-04-08 19:15:00": {
            "1. open": "490.3600",
            "2. high": "490.4300",
            "3. low": "488.5000",
            "4. close": "489.5800",
            "5. volume": "87946"
        },
        "2025-04-08 19:10:00": {
            "1. open": "491.0800",
            "2. high": "491.1000",
            "3. low": "490.3400",
            "4. close": "490.3600",
            "5. volume": "20407"
        },
        "2025-04-08 19:05:00": {
            "1. open": "491.0000",
            "2. high": "491.3600",
            "3. low": "490.4100",
            "4. close": "491.0050",
            "5. volume": "39780"
        },
        "2025-04-08 19:00:00": {
            "1. open": "492.4000",
            "2. high": "492.4000",
            "3. low": "490.8500",
            "4. close": "491.1400",
            "5. volume": "43174"
        },
        "2025-04-08 18:55:00": {
            "1. open": "492.0110",
            "2. high": "492.5900",
            "3. low": "491.7500",
            "4. close": "492.4000",
            "5. volume": "23271"
        },
        "2025-04-08 18:50:00": {
            "1. open": "492.0388",
            "2. high": "492.7000",
            "3. low": "491.5900",
            "4. close": "492.1800",
            "5. volume": "24256"
        },
        "2025-04-08 18:45:00": {
            "1. open": "491.7000",
            "2. high": "492.3000",
            "3. low": "491.5000",
            "4. close": "492.0001",
            "5. volume": "27156"
        },
        "2025-04-08 18:40:00": {
            "1. open": "491.3050",
            "2. high": "523.8600",
            "3. low": "490.3500",
            "4. close": "491.6600",
            "5. volume": "21099"
        },
        "2025-04-08 18:35:00": {
            "1. open": "491.3500",
            "2. high": "491.7800",
            "3. low": "490.2000",
            "4. close": "491.3400",
            "5. volume": "29237"
        },
        "2025-04-08 18:30:00": {
            "1. open": "496.4800",
            "2. high": "496.4800",
            "3. low": "490.9800",
            "4. close": "491.1700",
            "5. volume": "3028503"
        },
        "2025-04-08 18:25:00": {
            "1. open": "490.8000",
            "2. high": "491.9900",
            "3. low": "490.5500",
            "4. close": "491.3801",
            "5. volume": "47769"
        },
        "2025-04-08 18:20:00": {
            "1. open": "492.0200",
            "2. high": "492.4900",
            "3. low": "489.9300",
            "4. close": "490.6750",
            "5. volume": "144737"
        },
        "2025-04-08 18:15:00": {
            "1. open": "492.7009",
            "2. high": "492.9500",
            "3. low": "491.5000",
            "4. close": "492.0100",
            "5. volume": "103715"
        },
        "2025-04-08 18:10:00": {
            "1. open": "492.7000",
            "2. high": "493.2300",
            "3. low": "492.3300",
            "4. close": "492.7350",
            "5. volume": "56870"
        },
        "2025-04-08 18:05:00": {
            "1. open": "492.9100",
            "2. high": "493.7200",
            "3. low": "492.0000",
            "4. close": "492.6900",
            "5. volume": "179788"
        },
        "2025-04-08 18:00:00": {
            "1. open": "495.8500",
            "2. high": "496.2200",
            "3. low": "492.0000",
            "4. close": "492.9100",
            "5. volume": "229303"
        },
        "2025-04-08 17:55:00": {
            "1. open": "496.2500",
            "2. high": "496.2500",
            "3. low": "495.8500",
            "4. close": "495.8500",
            "5. volume": "21218"
        },
        "2025-04-08 17:50:00": {
            "1. open": "496.2800",
            "2. high": "496.4800",
            "3. low": "496.1850",
            "4. close": "496.2492",
            "5. volume": "162260"
        },
        "2025-04-08 17:45:00": {
            "1. open": "496.1600",
            "2. high": "496.5000",
            "3. low": "496.1500",
            "4. close": "496.3000",
            "5. volume": "111909"
        },
        "2025-04-08 17:40:00": {
            "1. open": "496.1982",
            "2. high": "496.3900",
            "3. low": "496.1000",
            "4. close": "496.2000",
            "5. volume": "25545"
        },
        "2025-04-08 17:35:00": {
            "1. open": "496.0300",
            "2. high": "496.2600",
            "3. low": "496.0300",
            "4. close": "496.1350",
            "5. volume": "7514"
        },
        "2025-04-08 17:30:00": {
            "1. open": "495.7700",
            "2. high": "496.3900",
            "3. low": "495.7300",
            "4. close": "496.0600",
            "5. volume": "16346"
        },
        "2025-04-08 17:25:00": {
            "1. open": "495.6900",
            "2. high": "495.9200",
            "3. low": "495.5500",
            "4. close": "495.7600",
            "5. volume": "22087"
        },
        "2025-04-08 17:20:00": {
            "1. open": "495.5900",
            "2. high": "495.7600",
            "3. low": "495.5000",
            "4. close": "495.7000",
            "5. volume": "32212"
        },
        "2025-04-08 17:15:00": {
            "1. open": "495.8300",
            "2. high": "495.9400",
            "3. low": "495.5600",
            "4. close": "495.5891",
            "5. volume": "50688"
        },
        "2025-04-08 17:10:00": {
            "1. open": "495.8700",
            "2. high": "495.9300",
            "3. low": "495.6500",
            "4. close": "495.8100",
            "5. volume": "44738"
        },
        "2025-04-08 17:05:00": {
            "1. open": "496.1100",
            "2. high": "496.4800",
            "3. low": "495.8000",
            "4. close": "495.9000",
            "5. volume": "326593"
        },
        "2025-04-08 17:00:00": {
            "1. open": "496.0300",
            "2. high": "496.4800",
            "3. low": "495.8800",
            "4. close": "496.1000",
            "5. volume": "829401"
        },
        "2025-04-08 16:55:00": {
            "1. open": "495.9700",
            "2. high": "526.3113",
            "3. low": "495.6800",
            "4. close": "496.1500",
            "5. volume": "151369"
        },
        "2025-04-08 16:50:00": {
            "1. open": "496.0700",
            "2. high": "529.3134",
            "3. low": "467.2050",
            "4. close": "495.9850",
            "5. volume": "165439"
        },
        "2025-04-08 16:45:00": {
            "1. open": "495.2100",
            "2. high": "526.3113",
            "3. low": "494.5067",
            "4. close": "496.0688",
            "5. volume": "91176"
        },
        "2025-04-08 16:40:00": {
            "1. open": "494.8900",
            "2. high": "514.1142",
            "3. low": "494.7800",
            "4. close": "495.2350",
            "5. volume": "68914"
        },
        "2025-04-08 16:35:00": {
            "1. open": "494.7500",
            "2. high": "495.6800",
            "3. low": "494.7500",
            "4. close": "494.9300",
            "5. volume": "112622"
        },
        "2025-04-08 16:30:00": {
            "1. open": "494.6700",
            "2. high": "504.3800",
            "3. low": "494.6300",
            "4. close": "494.7800",
            "5. volume": "112295"
        },
        "2025-04-08 16:25:00": {
            "1. open": "494.2800",
            "2. high": "495.0000",
            "3. low": "493.9500",
            "4. close": "494.6800",
            "5. volume": "243927"
        },
        "2025-04-08 16:20:00": {
            "1. open": "496.0389",
            "2. high": "510.3403",
            "3. low": "494.2600",
            "4. close": "494.3568",
            "5. volume": "320212"
        },
        "2025-04-08 16:15:00": {
            "1. open": "496.2500",
            "2. high": "504.4170",
            "3. low": "495.6667",
            "4. close": "495.9950",
            "5. volume": "4031554"
        },
        "2025-04-08 16:10:00": {
            "1. open": "496.4800",
            "2. high": "497.6300",
            "3. low": "495.6667",
            "4. close": "496.2400",
            "5. volume": "3590824"
        },
        "2025-04-08 16:05:00": {
            "1. open": "496.8700",
            "2. high": "498.6600",
            "3. low": "496.3800",
            "4. close": "497.3300",
            "5. volume": "908039"
        },
        "2025-04-08 16:00:00": {
            "1. open": "496.7500",
            "2. high": "497.5000",
            "3. low": "486.2007",
            "4. close": "496.9300",
            "5. volume": "8066871"
        },
        "2025-04-08 15:55:00": {
            "1. open": "495.9300",
            "2. high": "497.4600",
            "3. low": "493.9400",
            "4. close": "496.7400",
            "5. volume": "8343352"
        },
        "2025-04-08 15:50:00": {
            "1. open": "489.3800",
            "2. high": "496.3600",
            "3. low": "489.3700",
            "4. close": "495.9300",
            "5. volume": "5201909"
        },
        "2025-04-08 15:45:00": {
            "1. open": "490.6300",
            "2. high": "491.6400",
            "3. low": "489.1600",
            "4. close": "489.3900",
            "5. volume": "4653352"
        },
        "2025-04-08 15:40:00": {
            "1. open": "491.5000",
            "2. high": "493.8000",
            "3. low": "490.5000",
            "4. close": "490.6050",
            "5. volume": "4284729"
        },
        "2025-04-08 15:35:00": {
            "1. open": "495.3200",
            "2. high": "495.3300",
            "3. low": "491.0000",
            "4. close": "491.4800",
            "5. volume": "4078884"
        },
        "2025-04-08 15:30:00": {
            "1. open": "497.5300",
            "2. high": "497.5900",
            "3. low": "495.2000",
            "4. close": "495.2900",
            "5. volume": "1845564"
        },
        "2025-04-08 15:25:00": {
            "1. open": "496.9800",
            "2. high": "498.6200",
            "3. low": "496.7900",
            "4. close": "497.5100",
            "5. volume": "2086726"
        },
        "2025-04-08 15:20:00": {
            "1. open": "495.0400",
            "2. high": "497.0700",
            "3. low": "494.7950",
            "4. close": "496.9900",
            "5. volume": "2387070"
        },
        "2025-04-08 15:15:00": {
            "1. open": "496.5808",
            "2. high": "496.9700",
            "3. low": "494.3400",
            "4. close": "495.1800",
            "5. volume": "2829403"
        },
        "2025-04-08 15:10:00": {
            "1. open": "497.6600",
            "2. high": "498.5600",
            "3. low": "496.3300",
            "4. close": "496.6100",
            "5. volume": "2018903"
        },
        "2025-04-08 15:05:00": {
            "1. open": "500.3600",
            "2. high": "500.7600",
            "3. low": "497.5600",
            "4. close": "497.6700",
            "5. volume": "2069385"
        },
        "2025-04-08 15:00:00": {
            "1. open": "501.7100",
            "2. high": "502.1200",
            "3. low": "500.1700",
            "4. close": "500.3700",
            "5. volume": "1045837"
        },
        "2025-04-08 14:55:00": {
            "1. open": "502.8500",
            "2. high": "503.0900",
            "3. low": "501.6300",
            "4. close": "501.6900",
            "5. volume": "842705"
        },
        "2025-04-08 14:50:00": {
            "1. open": "503.3550",
            "2. high": "504.1900",
            "3. low": "502.5500",
            "4. close": "502.8600",
            "5. volume": "890767"
        },
        "2025-04-08 14:45:00": {
            "1. open": "501.5300",
            "2. high": "504.0000",
            "3. low": "501.5300",
            "4. close": "503.3100",
            "5. volume": "1403519"
        },
        "2025-04-08 14:40:00": {
            "1. open": "502.7600",
            "2. high": "502.8600",
            "3. low": "501.4000",
            "4. close": "501.5290",
            "5. volume": "932633"
        },
        "2025-04-08 14:35:00": {
            "1. open": "503.5200",
            "2. high": "503.7100",
            "3. low": "501.6300",
            "4. close": "502.7600",
            "5. volume": "1437122"
        },
        "2025-04-08 14:30:00": {
            "1. open": "502.4400",
            "2. high": "507.8200",
            "3. low": "502.4400",
            "4. close": "503.5800",
            "5. volume": "3025404"
        },
        "2025-04-08 14:25:00": {
            "1. open": "504.9200",
            "2. high": "505.0300",
            "3. low": "502.0700",
            "4. close": "502.4100",
            "5. volume": "1120544"
        },
        "2025-04-08 14:20:00": {
            "1. open": "505.7900",
            "2. high": "505.9800",
            "3. low": "504.3300",
            "4. close": "504.9000",
            "5. volume": "877343"
        },
        "2025-04-08 14:15:00": {
            "1. open": "503.4200",
            "2. high": "506.1100",
            "3. low": "503.2150",
            "4. close": "505.7900",
            "5. volume": "1221093"
        },
        "2025-04-08 14:10:00": {
            "1. open": "504.4250",
            "2. high": "504.9100",
            "3. low": "503.0000",
            "4. close": "503.4000",
            "5. volume": "833120"
        },
        "2025-04-08 14:05:00": {
            "1. open": "505.9500",
            "2. high": "506.0200",
            "3. low": "503.8400",
            "4. close": "504.3800",
            "5. volume": "945605"
        },
        "2025-04-08 14:00:00": {
            "1. open": "506.7600",
            "2. high": "507.1200",
            "3. low": "505.4000",
            "4. close": "505.9300",
            "5. volume": "1056049"
        },
        "2025-04-08 13:55:00": {
            "1. open": "505.2400",
            "2. high": "507.0100",
            "3. low": "505.1500",
            "4. close": "506.7200",
            "5. volume": "741166"
        },
        "2025-04-08 13:50:00": {
            "1. open": "505.3000",
            "2. high": "506.9000",
            "3. low": "504.4800",
            "4. close": "505.2800",
            "5. volume": "1040545"
        },
        "2025-04-08 13:45:00": {
            "1. open": "507.8000",
            "2. high": "507.9300",
            "3. low": "505.0600",
            "4. close": "505.3300",
            "5. volume": "1437927"
        },
        "2025-04-08 13:40:00": {
            "1. open": "505.1200",
            "2. high": "509.1100",
            "3. low": "505.0400",
            "4. close": "507.7800",
            "5. volume": "2009030"
        },
        "2025-04-08 13:35:00": {
            "1. open": "502.3300",
            "2. high": "505.7300",
            "3. low": "502.0300",
            "4. close": "505.1400",
            "5. volume": "2910169"
        },
        "2025-04-08 13:30:00": {
            "1. open": "502.3700",
            "2. high": "503.7500",
            "3. low": "502.0900",
            "4. close": "502.2700",
            "5. volume": "1333139"
        },
        "2025-04-08 13:25:00": {
            "1. open": "504.5700",
            "2. high": "505.0800",
            "3. low": "502.2500",
            "4. close": "502.4500",
            "5. volume": "1550161"
        },
        "2025-04-08 13:20:00": {
            "1. open": "505.2500",
            "2. high": "505.6500",
            "3. low": "503.7000",
            "4. close": "504.5700",
            "5. volume": "1567736"
        },
        "2025-04-08 13:15:00": {
            "1. open": "505.0900",
            "2. high": "506.8000",
            "3. low": "504.8400",
            "4. close": "505.2600",
            "5. volume": "2424725"
        },
        "2025-04-08 13:10:00": {
            "1. open": "504.9000",
            "2. high": "505.6500",
            "3. low": "503.4700",
            "4. close": "505.0800",
            "5. volume": "2527619"
        },
        "2025-04-08 13:05:00": {
            "1. open": "507.6200",
            "2. high": "508.5700",
            "3. low": "504.7300",
            "4. close": "504.9280",
            "5. volume": "1873901"
        },
        "2025-04-08 13:00:00": {
            "1. open": "507.0800",
            "2. high": "507.8200",
            "3. low": "505.9000",
            "4. close": "507.6500",
            "5. volume": "1708912"
        },
        "2025-04-08 12:55:00": {
            "1. open": "509.2800",
            "2. high": "510.6000",
            "3. low": "507.0200",
            "4. close": "507.1442",
            "5. volume": "1570030"
        },
        "2025-04-08 12:50:00": {
            "1. open": "510.2300",
            "2. high": "510.7900",
            "3. low": "508.9400",
            "4. close": "509.2650",
            "5. volume": "1412018"
        },
        "2025-04-08 12:45:00": {
            "1. open": "508.5200",
            "2. high": "511.5000",
            "3. low": "508.0001",
            "4. close": "510.2500",
            "5. volume": "3546028"
        },
        "2025-04-08 12:40:00": {
            "1. open": "509.1400",
            "2. high": "509.7400",
            "3. low": "507.5800",
            "4. close": "508.5400",
            "5. volume": "2426581"
        },
        "2025-04-08 12:35:00": {
            "1. open": "511.9000",
            "2. high": "512.6600",
            "3. low": "508.6300",
            "4. close": "509.1400",
            "5. volume": "2165267"
        },
        "2025-04-08 12:30:00": {
            "1. open": "513.9500",
            "2. high": "514.6000",
            "3. low": "510.3800",
            "4. close": "511.9000",
            "5. volume": "2518809"
        },
        "2025-04-08 12:25:00": {
            "1. open": "512.1900",
            "2. high": "514.0000",
            "3. low": "511.8000",
            "4. close": "513.9600",
            "5. volume": "1146409"
        },
        "2025-04-08 12:20:00": {
            "1. open": "513.3700",
            "2. high": "513.7031",
            "3. low": "511.8600",
            "4. close": "512.2400",
            "5. volume": "1066891"
        },
        "2025-04-08 12:15:00": {
            "1. open": "515.3150",
            "2. high": "515.4900",
            "3. low": "513.0400",
            "4. close": "513.3600",
            "5. volume": "1088888"
        },
        "2025-04-08 12:10:00": {
            "1. open": "515.6200",
            "2. high": "516.9800",
            "3. low": "515.3000",
            "4. close": "515.3500",
            "5. volume": "1143212"
        },
        "2025-04-08 12:05:00": {
            "1. open": "516.4300",
            "2. high": "517.2900",
            "3. low": "515.4300",
            "4. close": "515.6400",
            "5. volume": "1113089"
        },
        "2025-04-08 12:00:00": {
            "1. open": "516.7400",
            "2. high": "516.9000",
            "3. low": "515.6800",
            "4. close": "516.4400",
            "5. volume": "598009"
        },
        "2025-04-08 11:55:00": {
            "1. open": "515.6000",
            "2. high": "517.0300",
            "3. low": "515.3200",
            "4. close": "516.7700",
            "5. volume": "1177133"
        },
        "2025-04-08 11:50:00": {
            "1. open": "515.7000",
            "2. high": "516.0450",
            "3. low": "514.2350",
            "4. close": "515.6000",
            "5. volume": "1011027"
        },
        "2025-04-08 11:45:00": {
            "1. open": "517.4100",
            "2. high": "518.1800",
            "3. low": "515.3600",
            "4. close": "515.6750",
            "5. volume": "846024"
        }
    }
}