{
    "Meta Data": {
        "1. Information": "Intraday (5min) open, high, low, close prices and volume",
        "2. Symbol": "GOOGL",
        "3. Last Refreshed": "2024-02-14 19:55:00",
        "4. Interval": "5min",
        "5. Output Size": "Compact",
        "6. Time Zone": "US/Eastern"
    },
    "Time Series (5min)": {
        "2024-02-14 19:55:00": {
            "1. open": "143.4600",
            "2. high": "143.4800",
            "3. low": "143.3000",
            "4. close": "143.4800",
            "5. volume": "5724"
        },
        "2024-02-14 19:50:00": {
            "1. open": "143.4600",
            "2. high": "143.4800",
            "3. low": "143.4000",
            "4. close": "143.4600",
            "5. volume": "4576"
        },
        "2024-02-14 19:45:00": {
            "1. open": "143.5000",
            "2. high": "143.5000",
            "3. low": "143.4100",
            "4. close": "143.4800",
            "5. volume": "1888"
        },
        "2024-02-14 19:40:00": {
            "1. open": "143.4600",
            "2. high": "143.5000",
            "3. low": "143.4100",
            "4. close": "143.5000",
            "5. volume": "4813"
        },
        "2024-02-14 19:35:00": {
            "1. open": "143.4900",
            "2. high": "143.5000",
            "3. low": "143.3500",
            "4. close": "143.4500",
            "5. volume": "5250"
        },
        "2024-02-14 19:30:00": {
            "1. open": "143.4900",
            "2. high": "143.5000",
            "3. low": "143.4500",
            "4. close": "143.4900",
            "5. volume": "1817"
        },
        "2024-02-14 19:25:00": {
            "1. open": "143.4600",
            "2. high": "143.4900",
            "3. low": "143.4500",
            "4. close": "143.4500",
            "5. volume": "1758"
        },
        "2024-02-14 19:20:00": {
            "1. open": "143.5000",
            "2. high": "143.5000",
            "3. low": "143.4500",
            "4. close": "143.4900",
            "5. volume": "964"
        },
        "2024-02-14 19:15:00": {
            "1. open": "143.4500",
            "2. high": "143.5000",
            "3. low": "143.4200",
            "4. close": "143.5000",
            "5. volume": "3707"
        },
        "2024-02-14 19:10:00": {
            "1. open": "143.4000",
            "2. high": "143.4600",
            "3. low": "143.3600",
            "4. close": "143.4500",
            "5. volume": "3202"
        },
        "2024-02-14 19:05:00": {
            "1. open": "143.4500",
            "2. high": "143.4500",
            "3. low": "143.3600",
            "4. close": "143.4000",
            "5. volume": "1279"
        },
        "2024-02-14 19:00:00": {
            "1. open": "143.5000",
            "2. high": "143.5000",
            "3. low": "143.3600",
            "4. close": "143.4500",
            "5. volume": "2418"
        },
        "2024-02-14 18:55:00": {
            "1. open": "143.4800",
            "2. high": "143.5000",
            "3. low": "143.4030",
            "4. close": "143.4900",
            "5. volume": "7812"
        },
        "2024-02-14 18:50:00": {
            "1. open": "143.3700",
            "2. high": "143.5000",
            "3. low": "143.3600",
            "4. close": "143.4800",
            "5. volume": "2948"
        },
        "2024-02-14 18:45:00": {
            "1. open": "143.4300",
            "2. high": "143.4500",
            "3. low": "143.3500",
            "4. close": "143.3700",
            "5. volume": "3280"
        },
        "2024-02-14 18:40:00": {
            "1. open": "143.4000",
            "2. high": "143.4900",
            "3. low": "143.3600",
            "4. close": "143.4500",
            "5. volume": "3209"
        },
        "2024-02-14 18:35:00": {
            "1. open": "143.3500",
            "2. high": "143.4500",
            "3. low": "143.3400",
            "4. close": "143.4000",
            "5. volume": "3414"
        },
        "2024-02-14 18:30:00": {
            "1. open": "143.3500",
            "2. high": "143.3500",
            "3. low": "143.2500",
            "4. close": "143.3400",
            "5. volume": "5705"
        },
        "2024-02-14 18:25:00": {
            "1. open": "143.1700",
            "2. high": "143.3500",
            "3. low": "143.1100",
            "4. close": "143.3000",
            "5. volume": "3658"
        },
        "2024-02-14 18:20:00": {
            "1. open": "143.0000",
            "2. high": "143.2100",
            "3. low": "143.0000",
            "4. close": "143.2000",
            "5. volume": "2467"
        },
        "2024-02-14 18:15:00": {
            "1. open": "143.0000",
            "2. high": "143.0000",
            "3. low": "142.8500",
            "4. close": "143.0000",
            "5. volume": "2936"
        },
        "2024-02-14 18:10:00": {
            "1. open": "142.9900",
            "2. high": "143.0000",
            "3. low": "142.6500",
            "4. close": "142.9100",
            "5. volume": "18176"
        },
        "2024-02-14 18:05:00": {
            "1. open": "143.0000",
            "2. high": "143.0000",
            "3. low": "142.9100",
            "4. close": "142.9500",
            "5. volume": "19021"
        },
        "2024-02-14 18:00:00": {
            "1. open": "143.0000",
            "2. high": "143.0000",
            "3. low": "142.9100",
            "4. close": "143.0000",
            "5. volume": "2062"
        },
        "2024-02-14 17:55:00": {
            "1. open": "143.2500",
            "2. high": "143.3000",
            "3. low": "142.9000",
            "4. close": "143.0000",
            "5. volume": "31085"
        },
        "2024-02-14 17:50:00": {
            "1. open": "143.4000",
            "2. high": "143.4900",
            "3. low": "143.0000",
            "4. close": "143.3000",
            "5. volume": "15837"
        },
        "2024-02-14 17:45:00": {
            "1. open": "143.4500",
            "2. high": "145.9400",
            "3. low": "143.2000",
            "4. close": "143.4000",
            "5. volume": "14712"
        },
        "2024-02-14 17:40:00": {
            "1. open": "143.5500",
            "2. high": "143.5600",
            "3. low": "143.4000",
            "4. close": "143.4500",
            "5. volume": "4918"
        },
        "2024-02-14 17:35:00": {
            "1. open": "143.3500",
            "2. high": "143.5900",
            "3. low": "143.3400",
            "4. close": "143.5500",
            "5. volume": "3049"
        },
        "2024-02-14 17:30:00": {
            "1. open": "143.3500",
            "2. high": "143.5600",
            "3. low": "143.3000",
            "4. close": "143.3500",
            "5. volume": "11730"
        },
        "2024-02-14 17:25:00": {
            "1. open": "143.0800",
            "2. high": "145.9400",
            "3. low": "143.0200",
            "4. close": "143.3500",
            "5. volume": "31611"
        },
        "2024-02-14 17:20:00": {
            "1. open": "142.9500",
            "2. high": "143.0800",
            "3. low": "142.9000",
            "4. close": "143.0800",
            "5. volume": "11207"
        },
        "2024-02-14 17:15:00": {
            "1. open": "142.8000",
            "2. high": "145.9400",
            "3. low": "142.7500",
            "4. close": "142.9490",
            "5. volume": "40712"
        },
        "2024-02-14 17:10:00": {
            "1. open": "143.1700",
            "2. high": "143.2000",
            "3. low": "142.7000",
            "4. close": "142.8890",
            "5. volume": "29339"
        },
        "2024-02-14 17:05:00": {
            "1. open": "143.5940",
            "2. high": "143.6800",
            "3. low": "143.1600",
            "4. close": "143.1600",
            "5. volume": "25732"
        },
        "2024-02-14 17:00:00": {
            "1. open": "143.3200",
            "2. high": "143.6800",
            "3. low": "143.2500",
            "4. close": "143.6400",
            "5. volume": "59823"
        },
        "2024-02-14 16:55:00": {
            "1. open": "142.7300",
            "2. high": "143.3900",
            "3. low": "142.5300",
            "4. close": "143.3200",
            "5. volume": "78794"
        },
        "2024-02-14 16:50:00": {
            "1. open": "142.5400",
            "2. high": "145.9400",
            "3. low": "142.5100",
            "4. close": "142.7000",
            "5. volume": "281572"
        },
        "2024-02-14 16:45:00": {
            "1. open": "143.0000",
            "2. high": "143.4000",
            "3. low": "141.7700",
            "4. close": "142.8800",
            "5. volume": "233877"
        },
        "2024-02-14 16:40:00": {
            "1. open": "143.4200",
            "2. high": "144.1000",
            "3. low": "142.7500",
            "4. close": "143.0000",
            "5. volume": "129002"
        },
        "2024-02-14 16:35:00": {
            "1. open": "144.8600",
            "2. high": "144.9000",
            "3. low": "142.8000",
            "4. close": "143.3200",
            "5. volume": "137736"
        },
        "2024-02-14 16:30:00": {
            "1. open": "145.9900",
            "2. high": "145.9900",
            "3. low": "144.5100",
            "4. close": "144.8000",
            "5. volume": "46867"
        },
        "2024-02-14 16:25:00": {
            "1. open": "145.8500",
            "2. high": "146.0000",
            "3. low": "145.8300",
            "4. close": "145.9600",
            "5. volume": "7833"
        },
        "2024-02-14 16:20:00": {
            "1. open": "145.9400",
            "2. high": "145.9500",
            "3. low": "145.8200",
            "4. close": "145.8500",
            "5. volume": "50005"
        },
        "2024-02-14 16:15:00": {
            "1. open": "145.9400",
            "2. high": "145.9600",
            "3. low": "145.8100",
            "4. close": "145.8900",
            "5. volume": "1913"
        },
        "2024-02-14 16:10:00": {
            "1. open": "145.8800",
            "2. high": "145.9500",
            "3. low": "145.8100",
            "4. close": "145.8900",
            "5. volume": "17240"
        },
        "2024-02-14 16:05:00": {
            "1. open": "145.9100",
            "2. high": "146.0500",
            "3. low": "144.6400",
            "4. close": "145.9000",
            "5. volume": "83674"
        },
        "2024-02-14 16:00:00": {
            "1. open": "145.8600",
            "2. high": "145.9800",
            "3. low": "145.2580",
            "4. close": "145.9100",
            "5. volume": "6477191"
        },
        "2024-02-14 15:55:00": {
            "1. open": "145.8200",
            "2. high": "146.0200",
            "3. low": "145.8100",
            "4. close": "145.8600",
            "5. volume": "1177120"
        },
        "2024-02-14 15:50:00": {
            "1. open": "145.8700",
            "2. high": "145.9890",
            "3. low": "145.7780",
            "4. close": "145.8100",
            "5. volume": "448015"
        },
        "2024-02-14 15:45:00": {
            "1. open": "145.7150",
            "2. high": "145.8950",
            "3. low": "145.6800",
            "4. close": "145.8800",
            "5. volume": "276419"
        },
        "2024-02-14 15:40:00": {
            "1. open": "145.6900",
            "2. high": "145.7600",
            "3. low": "145.6300",
            "4. close": "145.7150",
            "5. volume": "270507"
        },
        "2024-02-14 15:35:00": {
            "1. open": "145.4850",
            "2. high": "145.7100",
            "3. low": "145.4830",
            "4. close": "145.7000",
            "5. volume": "173017"
        },
        "2024-02-14 15:30:00": {
            "1. open": "145.5950",
            "2. high": "145.6200",
            "3. low": "145.4000",
            "4. close": "145.4850",
            "5. volume": "256692"
        },
        "2024-02-14 15:25:00": {
            "1. open": "145.4000",
            "2. high": "145.6600",
            "3. low": "145.3930",
            "4. close": "145.5990",
            "5. volume": "248810"
        },
        "2024-02-14 15:20:00": {
            "1. open": "145.3300",
            "2. high": "145.4280",
            "3. low": "145.3300",
            "4. close": "145.3950",
            "5. volume": "156862"
        },
        "2024-02-14 15:15:00": {
            "1. open": "145.2900",
            "2. high": "145.3450",
            "3. low": "145.2500",
            "4. close": "145.3350",
            "5. volume": "152550"
        },
        "2024-02-14 15:10:00": {
            "1. open": "145.3300",
            "2. high": "145.3450",
            "3. low": "145.2490",
            "4. close": "145.2900",
            "5. volume": "156033"
        },
        "2024-02-14 15:05:00": {
            "1. open": "145.1650",
            "2. high": "145.3200",
            "3. low": "145.1600",
            "4. close": "145.3200",
            "5. volume": "145668"
        },
        "2024-02-14 15:00:00": {
            "1. open": "145.0850",
            "2. high": "145.1800",
            "3. low": "144.9850",
            "4. close": "145.1650",
            "5. volume": "198832"
        },
        "2024-02-14 14:55:00": {
            "1. open": "145.0400",
            "2. high": "145.0930",
            "3. low": "144.9400",
            "4. close": "145.0900",
            "5. volume": "115073"
        },
        "2024-02-14 14:50:00": {
            "1. open": "145.1500",
            "2. high": "145.1500",
            "3. low": "145.0250",
            "4. close": "145.0500",
            "5. volume": "85181"
        },
        "2024-02-14 14:45:00": {
            "1. open": "145.1100",
            "2. high": "145.1600",
            "3. low": "145.0200",
            "4. close": "145.1550",
            "5. volume": "125751"
        },
        "2024-02-14 14:40:00": {
            "1. open": "145.1200",
            "2. high": "145.1900",
            "3. low": "145.0400",
            "4. close": "145.1150",
            "5. volume": "134340"
        },
        "2024-02-14 14:35:00": {
            "1. open": "145.0800",
            "2. high": "145.1960",
            "3. low": "145.0600",
            "4. close": "145.1200",
            "5. volume": "108515"
        },
        "2024-02-14 14:30:00": {
            "1. open": "144.9900",
            "2. high": "145.0900",
            "3. low": "144.9600",
            "4. close": "145.0800",
            "5. volume": "133183"
        },
        "2024-02-14 14:25:00": {
            "1. open": "144.8850",
            "2. high": "145.0100",
            "3. low": "144.8750",
            "4. close": "144.9900",
            "5. volume": "111761"
        },
        "2024-02-14 14:20:00": {
            "1. open": "144.7800",
            "2. high": "144.9400",
            "3. low": "144.7750",
            "4. close": "144.8800",
            "5. volume": "85520"
        },
        "2024-02-14 14:15:00": {
            "1. open": "144.8800",
            "2. high": "144.9200",
            "3. low": "144.7650",
            "4. close": "144.7700",
            "5. volume": "103375"
        },
        "2024-02-14 14:10:00": {
            "1. open": "144.7690",
            "2. high": "144.9200",
            "3. low": "144.7050",
            "4. close": "144.8800",
            "5. volume": "240001"
        },
        "2024-02-14 14:05:00": {
            "1. open": "145.0100",
            "2. high": "145.0100",
            "3. low": "144.7100",
            "4. close": "144.7650",
            "5. volume": "167059"
        },
        "2024-02-14 14:00:00": {
            "1. open": "145.1220",
            "2. high": "145.1500",
            "3. low": "145.0090",
            "4. close": "145.0300",
            "5. volume": "119118"
        },
        "2024-02-14 13:55:00": {
            "1. open": "145.2500",
            "2. high": "145.2500",
            "3. low": "144.9990",
            "4. close": "145.1200",
            "5. volume": "114766"
        },
        "2024-02-14 13:50:00": {
            "1. open": "145.2300",
            "2. high": "145.2700",
            "3. low": "145.2030",
            "4. close": "145.2450",
            "5. volume": "84538"
        },
        "2024-02-14 13:45:00": {
            "1. open": "145.1600",
            "2. high": "145.3000",
            "3. low": "145.1430",
            "4. close": "145.2280",
            "5. volume": "99549"
        },
        "2024-02-14 13:40:00": {
            "1. open": "145.2500",
            "2. high": "145.2900",
            "3. low": "145.1300",
            "4. close": "145.1460",
            "5. volume": "97767"
        },
        "2024-02-14 13:35:00": {
            "1. open": "145.0700",
            "2. high": "145.2490",
            "3. low": "145.0690",
            "4. close": "145.2350",
            "5. volume": "177621"
        },
        "2024-02-14 13:30:00": {
            "1. open": "144.8500",
            "2. high": "145.0950",
            "3. low": "144.8000",
            "4. close": "145.0550",
            "5. volume": "135551"
        },
        "2024-02-14 13:25:00": {
            "1. open": "144.7200",
            "2. high": "144.8500",
            "3. low": "144.7100",
            "4. close": "144.8400",
            "5. volume": "136767"
        },
        "2024-02-14 13:20:00": {
            "1. open": "144.7000",
            "2. high": "144.8050",
            "3. low": "144.6800",
            "4. close": "144.7100",
            "5. volume": "77659"
        },
        "2024-02-14 13:15:00": {
            "1. open": "144.7000",
            "2. high": "144.8250",
            "3. low": "144.6700",
            "4. close": "144.6900",
            "5. volume": "66961"
        },
        "2024-02-14 13:10:00": {
            "1. open": "144.8140",
            "2. high": "144.8140",
            "3. low": "144.6100",
            "4. close": "144.6800",
            "5. volume": "131143"
        },
        "2024-02-14 13:05:00": {
            "1. open": "144.9790",
            "2. high": "145.0250",
            "3. low": "144.8150",
            "4. close": "144.8300",
            "5. volume": "117362"
        },
        "2024-02-14 13:00:00": {
            "1. open": "144.8500",
            "2. high": "145.0050",
            "3. low": "144.7900",
            "4. close": "144.9800",
            "5. volume": "112746"
        },
        "2024-02-14 12:55:00": {
            "1. open": "144.9150",
            "2. high": "144.9750",
            "3. low": "144.8250",
            "4. close": "144.8450",
            "5. volume": "120756"
        },
        "2024-02-14 12:50:00": {
            "1. open": "144.9900",
            "2. high": "145.0000",
            "3. low": "144.8950",
            "4. close": "144.9150",
            "5. volume": "820673"
        },
        "2024-02-14 12:45:00": {
            "1. open": "145.0450",
            "2. high": "145.0880",
            "3. low": "144.9500",
            "4. close": "144.9900",
            "5. volume": "90849"
        },
        "2024-02-14 12:40:00": {
            "1. open": "144.9950",
            "2. high": "145.1000",
            "3. low": "144.9250",
            "4. close": "145.0300",
            "5. volume": "157788"
        },
        "2024-02-14 12:35:00": {
            "1. open": "145.0550",
            "2. high": "145.0950",
            "3. low": "144.9550",
            "4. close": "144.9900",
            "5. volume": "181954"
        },
        "2024-02-14 12:30:00": {
            "1. open": "144.8000",
            "2. high": "145.0600",
            "3. low": "144.7820",
            "4. close": "145.0600",
            "5. volume": "184592"
        },
        "2024-02-14 12:25:00": {
            "1. open": "144.5290",
            "2. high": "144.8000",
            "3. low": "144.5200",
            "4. close": "144.7900",
            "5. volume": "127999"
        },
        "2024-02-14 12:20:00": {
            "1. open": "144.4700",
            "2. high": "144.5800",
            "3. low": "144.3950",
            "4. close": "144.5400",
            "5. volume": "149891"
        },
        "2024-02-14 12:15:00": {
            "1. open": "144.4700",
            "2. high": "144.5800",
            "3. low": "144.4600",
            "4. close": "144.4640",
            "5. volume": "109920"
        },
        "2024-02-14 12:10:00": {
            "1. open": "144.3600",
            "2. high": "144.5600",
            "3. low": "144.3600",
            "4. close": "144.4800",
            "5. volume": "117893"
        },
        "2024-02-14 12:05:00": {
            "1. open": "144.2000",
            "2. high": "144.4100",
            "3. low": "144.0940",
            "4. close": "144.3550",
            "5. volume": "215562"
        },
        "2024-02-14 12:00:00": {
            "1. open": "144.3800",
            "2. high": "144.4150",
            "3. low": "144.1300",
            "4. close": "144.2100",
            "5. volume": "224664"
        },
        "2024-02-14 11:55:00": {
            "1. open": "144.5700",
            "2. high": "144.6300",
            "3. low": "144.3300",
            "4. close": "144.3800",
            "5. volume": "181590"
        },
        "2024-02-14 11:50:00": {
            "1. open": "144.5900",
            "2. high": "144.6550",
            "3. low": "144.5200",
            "4. close": "144.5500",
            "5. volume": "123351"
        },
        "2024-02-14 11:45:00": {
            "1. open": "144.4100",
            "2. high": "144.6600",
            "3. low": "144.3600",
            "4. close": "144.6000",
            "5. volume": "156946"
        },
        "2024-02-14 11:40:00": {
            "1. open": "144.8410",
            "2. high": "144.9000",
            "3. low": "144.4050",
            "4. close": "144.4100",
            "5. volume": "277812"
        }
    }
}